UQToolbox/CutANOVA.py
UQToolbox/ModelReduction.py
UQToolbox/RandomSampling.py
UQToolbox/__init__.py
UQToolbox/_version.py
UQToolbox/auxiliary.py
UQToolbox/gPC.py
UQToolbox/mcmc.py
UQToolbox/sobol_lib.py
UQToolbox/unittests/TestCutANOVA.py
UQToolbox/unittests/TestKL1D.py
UQToolbox/unittests/TestKL2D.py
UQToolbox/unittests/TestRandomSampling.py
UQToolbox/unittests/TestTimingPreFit.py
UQToolbox/unittests/__init__.py
UQToolbox/unittests/auxiliary.py
UQToolbox/unittests/run_unit_tests.py
UQToolbox-1.0.4.dist-info/COPYING
UQToolbox-1.0.4.dist-info/COPYING.LESSER
UQToolbox-1.0.4.dist-info/METADATA
UQToolbox-1.0.4.dist-info/WHEEL
UQToolbox-1.0.4.dist-info/top_level.txt
UQToolbox-1.0.4.dist-info/RECORD
