Metadata-Version: 2.1
Name: UQToolbox
Version: 1.0.4
Summary: Tools for Uncertainty Quantification
Home-page: http://www2.compute.dtu.dk/~dabi/
Author: Daniele Bigoni
Author-email: dabi@dtu.dk
License: COPYING.LESSER
Platform: UNKNOWN
Requires-Dist: scipy
Requires-Dist: Sphinx
Requires-Dist: sphinxcontrib-bibtex
Requires-Dist: SpectralToolbox
Requires-Dist: prettytable
